{
  "id": "cmlzhceeg0007m2p34a89gpxv",
  "courseId": "cmlzhceef0004m2p3s0e463gm",
  "courseTitle": "Introduction to Algebra",
  "title": "Solving Linear Equations",
  "description": "One-step and multi-step equations",
  "content": "# Solving Linear Equations\n\nA linear equation is an equation where the highest power of the variable is 1. To solve, isolate the variable using inverse operations.\n\n## Resources\n\n- [Resource 1](https://openstax.org/books/elementary-algebra-2e/pages/2-1-solve-equations-using-the-subtraction-and-addition-properties-of-equality)",
  "order": 1,
  "status": "PUBLIC",
  "tier": "free",
  "category": "MATH",
  "links": [
    "https://openstax.org/books/elementary-algebra-2e/pages/2-1-solve-equations-using-the-subtraction-and-addition-properties-of-equality"
  ],
  "createdAt": "2026-02-23T17:58:07.336Z"
}