{
  "id": "cmm6gtjx2005k9of2w59tqyvy",
  "courseId": "cmm6gtjx2005i9of2g9s3gxik",
  "courseTitle": "Digital Photography",
  "title": "Understanding Exposure",
  "description": "Aperture, shutter speed, ISO",
  "content": "# Understanding Exposure\n\nThe exposure triangle: aperture controls depth of field, shutter speed controls motion blur, ISO controls sensitivity.\n\n## Resources\n\n- [Resource 1](https://www.cambridgeincolour.com/tutorials/camera-exposure.htm)",
  "order": 0,
  "status": "PUBLIC",
  "tier": "free",
  "category": "ARTS",
  "links": [
    "https://www.cambridgeincolour.com/tutorials/camera-exposure.htm"
  ],
  "createdAt": "2026-02-28T15:17:51.255Z"
}