{
  "id": "cmm10bd5u0054we8oepx4uc5g",
  "courseId": "cmm10bd5u0050we8oty8195uz",
  "courseTitle": "Music Theory Basics",
  "title": "Chords and Harmony",
  "description": "Building chords",
  "content": "# Chords and Harmony\n\nChords are three or more notes played together. Major chords sound happy; minor chords sound sad.\n\n## Resources\n\n- [Resource 1](https://www.musictheory.net/lessons/40)",
  "order": 2,
  "status": "PUBLIC",
  "tier": "free",
  "category": "ARTS",
  "links": [
    "https://www.musictheory.net/lessons/40"
  ],
  "createdAt": "2026-02-24T19:36:57.954Z"
}